recaptcha/__init__.py
recaptcha/admin.py
recaptcha/apps.py
recaptcha/forms.py
recaptcha/sites.py
recaptcha/captcha/__init__.py
recaptcha/captcha/apps.py
recaptcha/captcha/checks.py
recaptcha/captcha/client.py
recaptcha/captcha/constants.py
recaptcha/captcha/fields.py
recaptcha/captcha/widgets.py
recaptcha/captcha/tests/__init__.py
recaptcha/captcha/tests/test_client.py
recaptcha/captcha/tests/test_fields.py
recaptcha/captcha/tests/tests.py
recaptcha/captcha/tests/settings/__init__.py
recaptcha/captcha/tests/settings/coveralls_settings.py
Django_recaptcha_admin_login-2.0.dist-info/LICENSE
Django_recaptcha_admin_login-2.0.dist-info/METADATA
Django_recaptcha_admin_login-2.0.dist-info/WHEEL
Django_recaptcha_admin_login-2.0.dist-info/top_level.txt
Django_recaptcha_admin_login-2.0.dist-info/RECORD
