Metadata-Version: 2.1
Name: Django-recaptcha-admin-login
Version: 2.0
Summary: Django package to add Google reCAPTCHA to the admin login page
Author-email: arianminooei@gmail.com
Maintainer: Arian
Maintainer-email: arianminooei@gmail.com
Classifier: Framework :: Django :: 4.2
Classifier: Framework :: Django :: 5.0
Classifier: Programming Language :: Python :: 3.8
Classifier: Programming Language :: Python :: 3.9
Classifier: Programming Language :: Python :: 3.1
License-File: LICENSE
